paper_download_mcp/__init__.py
paper_download_mcp/__main__.py
paper_download_mcp/formatters.py
paper_download_mcp/models.py
paper_download_mcp/server.py
paper_download_mcp/scihub_core/__init__.py
paper_download_mcp/scihub_core/client.py
paper_download_mcp/scihub_core/metadata_utils.py
paper_download_mcp/scihub_core/scihub_dl_refactored.py
paper_download_mcp/scihub_core/config/__init__.py
paper_download_mcp/scihub_core/config/mirrors.py
paper_download_mcp/scihub_core/config/settings.py
paper_download_mcp/scihub_core/config/user_config.py
paper_download_mcp/scihub_core/core/__init__.py
paper_download_mcp/scihub_core/core/doi_processor.py
paper_download_mcp/scihub_core/core/downloader.py
paper_download_mcp/scihub_core/core/file_manager.py
paper_download_mcp/scihub_core/core/mirror_manager.py
paper_download_mcp/scihub_core/core/parser.py
paper_download_mcp/scihub_core/core/source_manager.py
paper_download_mcp/scihub_core/core/year_detector.py
paper_download_mcp/scihub_core/network/__init__.py
paper_download_mcp/scihub_core/network/session.py
paper_download_mcp/scihub_core/sources/__init__.py
paper_download_mcp/scihub_core/sources/arxiv_source.py
paper_download_mcp/scihub_core/sources/base.py
paper_download_mcp/scihub_core/sources/core_source.py
paper_download_mcp/scihub_core/sources/scihub_source.py
paper_download_mcp/scihub_core/sources/unpaywall_source.py
paper_download_mcp/scihub_core/utils/logging.py
paper_download_mcp/scihub_core/utils/retry.py
paper_download_mcp/tools/__init__.py
paper_download_mcp/tools/download.py
paper_download_mcp/tools/metadata.py
paper_download_mcp-0.2.0.dist-info/METADATA
paper_download_mcp-0.2.0.dist-info/WHEEL
paper_download_mcp-0.2.0.dist-info/entry_points.txt
paper_download_mcp-0.2.0.dist-info/licenses/LICENSE
paper_download_mcp-0.2.0.dist-info/RECORD
