Metadata-Version: 2.4
Name: paper-download-mcp
Version: 0.2.0
Summary: MCP server for downloading academic papers from multiple sources
Project-URL: Homepage, https://github.com/Oxidane-bot/paper-download-mcp
Project-URL: Documentation, https://github.com/Oxidane-bot/paper-download-mcp#readme
Project-URL: Repository, https://github.com/Oxidane-bot/paper-download-mcp
Project-URL: Issues, https://github.com/Oxidane-bot/paper-download-mcp/issues
Project-URL: Changelog, https://github.com/Oxidane-bot/paper-download-mcp/blob/main/CHANGELOG.md
Author-email: Oxidane <1317078257maroon@gmail.com>
License: MIT
License-File: LICENSE
Keywords: academic-papers,mcp,research,sci-hub,unpaywall
Classifier: Development Status :: 3 - Alpha
Classifier: Intended Audience :: Science/Research
Classifier: License :: OSI Approved :: MIT License
Classifier: Programming Language :: Python :: 3
Classifier: Programming Language :: Python :: 3.10
Classifier: Programming Language :: Python :: 3.11
Classifier: Programming Language :: Python :: 3.12
Requires-Python: >=3.10
Requires-Dist: beautifulsoup4>=4.12.0
Requires-Dist: lxml>=4.9.0
Requires-Dist: mcp[cli]>=1.0.0
Requires-Dist: pydantic>=2.0.0
Requires-Dist: requests>=2.31.0
Provides-Extra: dev
Requires-Dist: mypy>=1.0.0; extra == 'dev'
Requires-Dist: pytest-asyncio>=0.21.0; extra == 'dev'
Requires-Dist: pytest>=7.0.0; extra == 'dev'
Requires-Dist: ruff>=0.1.0; extra == 'dev'
